scrapybara_cli/callback.py
scrapybara_cli/main.py
scrapybara_cli-0.1.8.dist-info/METADATA
scrapybara_cli-0.1.8.dist-info/WHEEL
scrapybara_cli-0.1.8.dist-info/entry_points.txt
scrapybara_cli-0.1.8.dist-info/RECORD
