Metadata-Version: 2.4
Name: scrapybara-cli
Version: 0.1.8
Summary: CLI tool for controlling virtual machines with Claude
Author-email: Your Name <your.email@example.com>
Requires-Python: >=3.8
Requires-Dist: anthropic>=0.18.1
Requires-Dist: python-dotenv>=1.0.0
Requires-Dist: rich>=13.7.0
Requires-Dist: scrapybara>=0.1.0
Requires-Dist: typer>=0.9.0
